dm_aiomqtt/__init__.py
dm_aiomqtt/dm_aiomqtt_client.py
dm_aiomqtt/message_db.py
dm_aiomqtt-0.4.17.dist-info/METADATA
dm_aiomqtt-0.4.17.dist-info/WHEEL
dm_aiomqtt-0.4.17.dist-info/top_level.txt
dm_aiomqtt-0.4.17.dist-info/RECORD
