Metadata-Version: 2.4
Name: dm-aiomqtt
Version: 0.4.17
Summary: This is my custom aiomqtt client
Home-page: https://pypi.org/project/dm-aiomqtt
Author: dimka4621
Author-email: mismartconfig@gmail.com
Project-URL: GitHub, https://github.com/MykhLibs/dm-aiomqtt
Keywords: dm aiomqtt
Classifier: Programming Language :: Python :: 3.8
Classifier: License :: OSI Approved :: MIT License
Classifier: Operating System :: OS Independent
Requires-Python: >=3.8
Requires-Dist: dm-logger~=0.6.2
Requires-Dist: aiomqtt<3.0.0,>=2.0.1
Requires-Dist: aiofiles<24.0.0,>=23.2.1
Dynamic: author
Dynamic: author-email
Dynamic: classifier
Dynamic: description
Dynamic: description-content-type
Dynamic: home-page
Dynamic: keywords
Dynamic: project-url
Dynamic: requires-dist
Dynamic: requires-python
Dynamic: summary
